{
  "cmdline": ["/var/folders/bc/27hv15_d2zvcc3n3s9dxmfg00000gn/T/go-build308964871/command-line-arguments/_obj/exe/main","-l","debug","-s","i.sock","-c","realtest"],
  "memstats": {"Alloc":1254184,"TotalAlloc":2050072,"Sys":5703928,"Lookups":303,"Mallocs":10293,"Frees":5028,"HeapAlloc":1254184,"HeapSys":2097152,"HeapIdle":155648,"HeapInuse":1941504,"HeapReleased":0,"HeapObjects":5265,"StackInuse":204800,"StackSys":655360,"MSpanInuse":23040,"MSpanSys":32768,"MCacheInuse":8800,"MCacheSys":16384,"BuckHashSys":1441216,"GCSys":1183744,"OtherSys":277304,"NextGC":1608576,"LastGC":1417667597268161260,"PauseTotalNs":2567713,"PauseNs":[577976,238456,196489,271771,253912,559989,469120,0,0,0,0,0,0,0,0,0,0,0,0,0,0,0,0,0,0,0,0,0,0,0,0,0,0,0,0,0,0,0,0,0,0,0,0,0,0,0,0,0,0,0,0,0,0,0,0,0,0,0,0,0,0,0,0,0,0,0,0,0,0,0,0,0,0,0,0,0,0,0,0,0,0,0,0,0,0,0,0,0,0,0,0,0,0,0,0,0,0,0,0,0,0,0,0,0,0,0,0,0,0,0,0,0,0,0,0,0,0,0,0,0,0,0,0,0,0,0,0,0,0,0,0,0,0,0,0,0,0,0,0,0,0,0,0,0,0,0,0,0,0,0,0,0,0,0,0,0,0,0,0,0,0,0,0,0,0,0,0,0,0,0,0,0,0,0,0,0,0,0,0,0,0,0,0,0,0,0,0,0,0,0,0,0,0,0,0,0,0,0,0,0,0,0,0,0,0,0,0,0,0,0,0,0,0,0,0,0,0,0,0,0,0,0,0,0,0,0,0,0,0,0,0,0,0,0,0,0,0,0,0,0,0,0,0,0,0,0,0,0,0,0,0,0,0,0,0,0],"NumGC":7,"EnableGC":true,"DebugGC":false,"BySize":[{"Size":0,"Mallocs":0,"Frees":0},{"Size":8,"Mallocs":357,"Frees":174},{"Size":16,"Mallocs":1889,"Frees":831},{"Size":32,"Mallocs":3679,"Frees":1536},{"Size":48,"Mallocs":1497,"Frees":883},{"Size":64,"Mallocs":775,"Frees":534},{"Size":80,"Mallocs":353,"Frees":206},{"Size":96,"Mallocs":161,"Frees":87},{"Size":112,"Mallocs":285,"Frees":153},{"Size":128,"Mallocs":44,"Frees":18},{"Size":144,"Mallocs":223,"Frees":129},{"Size":160,"Mallocs":70,"Frees":26},{"Size":176,"Mallocs":37,"Frees":17},{"Size":192,"Mallocs":51,"Frees":37},{"Size":208,"Mallocs":222,"Frees":139},{"Size":224,"Mallocs":6,"Frees":6},{"Size":240,"Mallocs":9,"Frees":4},{"Size":256,"Mallocs":53,"Frees":23},{"Size":288,"Mallocs":101,"Frees":7},{"Size":320,"Mallocs":50,"Frees":27},{"Size":352,"Mallocs":3,"Frees":0},{"Size":384,"Mallocs":34,"Frees":14},{"Size":416,"Mallocs":14,"Frees":9},{"Size":448,"Mallocs":6,"Frees":6},{"Size":480,"Mallocs":2,"Frees":1},{"Size":512,"Mallocs":42,"Frees":23},{"Size":576,"Mallocs":9,"Frees":5},{"Size":640,"Mallocs":6,"Frees":2},{"Size":704,"Mallocs":3,"Frees":2},{"Size":768,"Mallocs":30,"Frees":16},{"Size":896,"Mallocs":19,"Frees":17},{"Size":1024,"Mallocs":14,"Frees":8},{"Size":1152,"Mallocs":25,"Frees":5},{"Size":1280,"Mallocs":2,"Frees":1},{"Size":1408,"Mallocs":3,"Frees":0},{"Size":1536,"Mallocs":30,"Frees":15},{"Size":1664,"Mallocs":14,"Frees":8},{"Size":2048,"Mallocs":53,"Frees":6},{"Size":2304,"Mallocs":6,"Frees":0},{"Size":2560,"Mallocs":1,"Frees":0},{"Size":2816,"Mallocs":0,"Frees":0},{"Size":3072,"Mallocs":0,"Frees":0},{"Size":3328,"Mallocs":2,"Frees":0},{"Size":4096,"Mallocs":58,"Frees":26},{"Size":4608,"Mallocs":0,"Frees":0},{"Size":5376,"Mallocs":1,"Frees":0},{"Size":6144,"Mallocs":0,"Frees":0},{"Size":6400,"Mallocs":2,"Frees":0},{"Size":6656,"Mallocs":0,"Frees":0},{"Size":6912,"Mallocs":0,"Frees":0},{"Size":8192,"Mallocs":23,"Frees":17},{"Size":8448,"Mallocs":0,"Frees":0},{"Size":8704,"Mallocs":0,"Frees":0},{"Size":9472,"Mallocs":0,"Frees":0},{"Size":10496,"Mallocs":0,"Frees":0},{"Size":12288,"Mallocs":0,"Frees":0},{"Size":13568,"Mallocs":0,"Frees":0},{"Size":14080,"Mallocs":0,"Frees":0},{"Size":16384,"Mallocs":13,"Frees":10},{"Size":16640,"Mallocs":0,"Frees":0},{"Size":17664,"Mallocs":0,"Frees":0}]}
}
